om/__init__.py
om/message/__init__.py
om/message/message.py
om/test/__init__.py
om/test/zmq_helper.py
om/utils/__init__.py
om/utils/alert_handler.py
om/utils/auth_provider.py
om/utils/charset.py
om/utils/config.py
om/utils/encryption.py
om/utils/filter.py
om/utils/healthz.py
om/utils/kv.py
om/utils/log_rotator.py
om/utils/matching.py
om/utils/package_reader.py
om/utils/rpc.py
om/utils/sentry.py
arivo.om-0.2.122.dist-info/METADATA
arivo.om-0.2.122.dist-info/WHEEL
arivo.om-0.2.122.dist-info/top_level.txt
arivo.om-0.2.122.dist-info/RECORD
