Metadata-Version: 2.1
Name: arivo.om
Version: 0.2.122
Summary: Util functions for om docker containers
Home-page: UNKNOWN
License: GPL-3
Platform: UNKNOWN
Classifier: Programming Language :: Python :: 2
Classifier: Programming Language :: Python :: 3
Requires-Python: >=2.6, !=3.0.*, !=3.1.*, !=3.2.*, <4
Requires-Dist: six
Requires-Dist: related
Requires-Dist: editdistance
Requires-Dist: sentry-sdk
Requires-Dist: pyyaml
Requires-Dist: pyzmq
Requires-Dist: enum34 ; python_version < "3.0"
